[
    {
        "name": "Manny Vazquez",
        "date": "2025-12-23"
    },
    {
        "name": "Michelle Waterson-Gomez",
        "date": "2025-12-23"
    },
    {
        "name": "Ricardo Romero",
        "date": "2025-12-23"
    },
    {
        "name": "Arman Tsarukyan",
        "date": "2026-01-15"
    },
    {
        "name": "Test Fighter",
        "date": "2026-01-15"
    },
    {
        "name": "Test Fighter",
        "date": "2026-01-15"
    },
    {
        "name": "Test Fighter",
        "date": "2026-01-15"
    },
    {
        "name": "Test Fighter",
        "date": "2026-01-15"
    },
    {
        "name": "Test Fighter",
        "date": "2026-01-15"
    },
    {
        "name": "Test Fighter",
        "date": "2026-01-15"
    },
    {
        "name": "Test Fighter",
        "date": "2026-01-15"
    },
    {
        "name": "Test Fighter",
        "date": "2026-01-15"
    },
    {
        "name": "Test Fighter",
        "date": "2026-01-15"
    },
    {
        "name": "Test Fighter",
        "date": "2026-01-15"
    },
    {
        "name": "Test Fighter",
        "date": "2026-01-15"
    },
    {
        "name": "Test Fighter",
        "date": "2026-01-15"
    },
    {
        "name": "Test Fighter",
        "date": "2026-01-15"
    },
    {
        "name": "Arman Tsarukyan",
        "date": "2026-01-15"
    },
    {
        "name": "Arman Tsarukyan",
        "date": "2026-01-15"
    },
    {
        "name": "Justin Gaethje",
        "date": "2026-01-15"
    },
    {
        "name": "Rani Yahya",
        "date": "2026-01-15"
    },
    {
        "name": "Arman Tsarukyan",
        "date": "2026-01-15"
    },
    {
        "name": "LC Davis",
        "date": "2026-01-15"
    },
    {
        "name": "Arman Tsarukyan",
        "date": "2026-01-15"
    },
    {
        "name": "Justin Gaethje",
        "date": "2026-01-15"
    },
    {
        "name": "Carlo Prater",
        "date": "2026-01-15"
    },
    {
        "name": "Khamzat Chimaev",
        "date": "2026-01-15"
    }
]